EDutils/__init__.py
EDutils/_version.py
EDutils/dials_utils.py
EDutils/display.py
EDutils/dyn_utils.py
EDutils/felix.py
EDutils/gui.py
EDutils/gui_config.py
EDutils/import_ED.py
EDutils/pets.py
EDutils/readers.py
EDutils/rotate_exp.py
EDutils/utilities.py
EDutils/viewers.py
EDutils/xds.py
blochwave/__init__.py
blochwave/_version.py
blochwave/bloch.py
blochwave/bloch2D.py
blochwave/bloch_pp.py
blochwave/util.py
multislice/ED_base.py
multislice/__init__.py
multislice/_version.py
multislice/config.py
multislice/import.py
multislice/interaction_parameter.py
multislice/multi_2D.py
multislice/multi_3D.py
multislice/multislice.py
multislice/mupy_utils.py
multislice/pets.py
multislice/postprocess.py
multislice/pymultislice.py
multislice/rotating_crystal.py
nearBragg/__init__.py
nearBragg/nearBragg.py
nearBragg/nearBragg_doc.py
nearBragg/proba.py
scattering/__init__.py
scattering/cmpScattering.py
scattering/potential.py
scattering/potential_misc.py
scattering/scattering_factors.py
scattering/splines.py
scattering/structure_factor.py
wallpp/__init__.py
wallpp/config.py
wallpp/gui.py
wallpp/lattice.py
wallpp/nodesTri.py
wallpp/plane_group.py
wallpp/space_group.py
wallpp/wallpaper.py
ccp4ED-1.6.dist-info/METADATA
ccp4ED-1.6.dist-info/WHEEL
ccp4ED-1.6.dist-info/top_level.txt
ccp4ED-1.6.dist-info/RECORD
