Metadata-Version: 2.1
Name: ccp4ED
Version: 1.6
Summary: Electron diffraction utilities
Home-page: https://pypi.org/project/ccp4ED
Author: Tarik Ronan Drevon
Author-email: tarik.drevon@stfc.ac.uk
License: UNKNOWN
Project-URL: Documentation, https://debloch.readthedocs.io/en/latest/
Project-URL: Source, https://github.com/ccp4/electron-diffraction
Platform: UNKNOWN
Classifier: Programming Language :: Python :: 3
Classifier: License :: OSI Approved :: MIT License 
Classifier: Operating System :: OS Independent
Requires-Python: >=3.6
Requires-Dist: TarikDrevonUtils
Requires-Dist: bs4
Requires-Dist: cbf
Requires-Dist: colorama
Requires-Dist: crystals
Requires-Dist: easygui
Requires-Dist: gemmi
Requires-Dist: matplotlib
Requires-Dist: mrcfile
Requires-Dist: numpy
Requires-Dist: opencv-python
Requires-Dist: pandas
Requires-Dist: pickle5
Requires-Dist: scipy
Requires-Dist: tifffile
Requires-Dist: wheel
